CHANGES.rst
CONTRIBUTORS.rst
DEVELOP.rst
LICENSE.GPL
LICENSE.rst
MANIFEST.in
README.rst
TODO.rst
setup.cfg
setup.py
docs/conf.py
docs/index.rst
src/collective/__init__.py
src/collective.bookmarks.egg-info/PKG-INFO
src/collective.bookmarks.egg-info/SOURCES.txt
src/collective.bookmarks.egg-info/dependency_links.txt
src/collective.bookmarks.egg-info/entry_points.txt
src/collective.bookmarks.egg-info/namespace_packages.txt
src/collective.bookmarks.egg-info/not-zip-safe
src/collective.bookmarks.egg-info/requires.txt
src/collective.bookmarks.egg-info/top_level.txt
src/collective/bookmarks/__init__.py
src/collective/bookmarks/configure.zcml
src/collective/bookmarks/interfaces.py
src/collective/bookmarks/permissions.zcml
src/collective/bookmarks/setuphandlers.py
src/collective/bookmarks/storage.py
src/collective/bookmarks/testing.py
src/collective/bookmarks/api/__init__.py
src/collective/bookmarks/api/configure.zcml
src/collective/bookmarks/api/utils.py
src/collective/bookmarks/api/services/__init__.py
src/collective/bookmarks/api/services/configure.zcml
src/collective/bookmarks/api/services/bookmark/__init__.py
src/collective/bookmarks/api/services/bookmark/configure.zcml
src/collective/bookmarks/api/services/bookmark/delete.py
src/collective/bookmarks/api/services/bookmark/get.py
src/collective/bookmarks/api/services/bookmark/post.py
src/collective/bookmarks/api/services/bookmark/put.py
src/collective/bookmarks/api/services/bookmarks/__init__.py
src/collective/bookmarks/api/services/bookmarks/configure.zcml
src/collective/bookmarks/api/services/bookmarks/get.py
src/collective/bookmarks/browser/__init__.py
src/collective/bookmarks/browser/configure.zcml
src/collective/bookmarks/browser/sample.pt
src/collective/bookmarks/browser/static/.gitkeep
src/collective/bookmarks/browser/static/collective.bookmarks.css
src/collective/bookmarks/browser/static/collective.bookmarks.css.map
src/collective/bookmarks/browser/static/collective.bookmarks.js
src/collective/bookmarks/browser/static/collective.bookmarks.js.map
src/collective/bookmarks/browser/static/index.html
src/collective/bookmarks/locales/README.rst
src/collective/bookmarks/locales/__init__.py
src/collective/bookmarks/locales/collective.bookmarks.pot
src/collective/bookmarks/locales/update.py
src/collective/bookmarks/locales/update.sh
src/collective/bookmarks/locales/en/LC_MESSAGES/collective.bookmarks.po
