Metadata-Version: 2.1
Name: collective.bookmarks
Version: 1.1
Summary: Bookmarks/ favorites (internal) for Plone
Home-page: https://github.com/collective/collective.bookmarks
Author: Jens W. Klein
Author-email: jk@kleinundpartner.at
License: GPL version 2
Project-URL: PyPI, https://pypi.python.org/pypi/collective.bookmarks
Project-URL: Source, https://github.com/collective/collective.bookmarks
Project-URL: Tracker, https://github.com/collective/collective.bookmarks/issues
Keywords: Python Plone
Classifier: Environment :: Web Environment
Classifier: Framework :: Plone
Classifier: Framework :: Plone :: Addon
Classifier: Framework :: Plone :: 5.2
Classifier: Framework :: Plone :: 6.0
Classifier: Programming Language :: Python
Classifier: Programming Language :: Python :: 3.7
Classifier: Programming Language :: Python :: 3.8
Classifier: Programming Language :: Python :: 3.9
Classifier: Programming Language :: Python :: 3.10
Classifier: Programming Language :: Python :: 3.11
Classifier: Operating System :: OS Independent
Classifier: License :: OSI Approved :: GNU General Public License v2 (GPLv2)
Requires-Python: >=3.7
Provides-Extra: test
License-File: LICENSE.GPL
License-File: LICENSE.rst
